pocomc_bilby/__init__.py
pocomc_bilby/plugin.py
pocomc_bilby/prior.py
pocomc_bilby-0.2.2.dist-info/licenses/LICENSE
pocomc_bilby-0.2.2.dist-info/METADATA
pocomc_bilby-0.2.2.dist-info/WHEEL
pocomc_bilby-0.2.2.dist-info/entry_points.txt
pocomc_bilby-0.2.2.dist-info/top_level.txt
pocomc_bilby-0.2.2.dist-info/RECORD
