Metadata-Version: 2.4
Name: pocomc-bilby
Version: 0.2.2
Summary: pocomc plugin for bilby
Author-email: "Michael J. Williams" <michaeljw1@googlemail.com>
License: MIT
Classifier: Programming Language :: Python :: 3
Requires-Python: >=3.9
License-File: LICENSE
Requires-Dist: bilby>=2.3.0
Requires-Dist: numpy
Requires-Dist: pocomc>=1.2.6
Requires-Dist: pandas
Provides-Extra: test
Requires-Dist: pytest; extra == "test"
Dynamic: license-file
